CHANGELOG.md
VERSION
lightbus/__init__.py
lightbus/api.py
lightbus/client/__init__.py
lightbus/client/bus_client.py
lightbus/client/commands.py
lightbus/client/docks/__init__.py
lightbus/client/docks/base.py
lightbus/client/docks/event.py
lightbus/client/docks/rpc_result.py
lightbus/client/internal_messaging/__init__.py
lightbus/client/internal_messaging/consumer.py
lightbus/client/internal_messaging/producer.py
lightbus/client/subclients/__init__.py
lightbus/client/subclients/base.py
lightbus/client/subclients/event.py
lightbus/client/subclients/rpc_result.py
lightbus/client/utilities.py
lightbus/client/validator.py
lightbus/commands/__init__.py
lightbus/commands/dump_config_schema.py
lightbus/commands/dump_schema.py
lightbus/commands/inspect.py
lightbus/commands/run.py
lightbus/commands/shell.py
lightbus/commands/utilities.py
lightbus/commands/version.py
lightbus/config/__init__.py
lightbus/config/config.py
lightbus/config/structure.py
lightbus/creation.py
lightbus/exceptions.py
lightbus/hooks.py
lightbus/internal_apis.py
lightbus/log.py
lightbus/message.py
lightbus/path.py
lightbus/plugins/__init__.py
lightbus/plugins/metrics.py
lightbus/plugins/state.py
lightbus/schema/__init__.py
lightbus/schema/encoder.py
lightbus/schema/hints_to_schema.py
lightbus/schema/schema.py
lightbus/serializers/__init__.py
lightbus/serializers/base.py
lightbus/serializers/blob.py
lightbus/serializers/by_field.py
lightbus/transports/__init__.py
lightbus/transports/base.py
lightbus/transports/debug.py
lightbus/transports/pool.py
lightbus/transports/redis/__init__.py
lightbus/transports/redis/event.py
lightbus/transports/redis/result.py
lightbus/transports/redis/rpc.py
lightbus/transports/redis/schema.py
lightbus/transports/redis/utilities.py
lightbus/transports/registry.py
lightbus/utilities/__init__.py
lightbus/utilities/async_tools.py
lightbus/utilities/casting.py
lightbus/utilities/config.py
lightbus/utilities/deforming.py
lightbus/utilities/django.py
lightbus/utilities/features.py
lightbus-1.1.2.dist-info/entry_points.txt
lightbus-1.1.2.dist-info/LICENSE.txt
lightbus-1.1.2.dist-info/WHEEL
lightbus-1.1.2.dist-info/METADATA
lightbus-1.1.2.dist-info/RECORD
