Metadata-Version: 2.1
Name: lightbus
Version: 1.1.2
Summary: RPC & event framework for Python 3
Home-page: https://lightbus.org
Keywords: python,messaging,redis,bus,queue
Author: Adam Charnock
Author-email: adam@adamcharnock.com
Requires-Python: >=3.7
Classifier: Development Status :: 5 - Production/Stable
Classifier: Framework :: AsyncIO
Classifier: Intended Audience :: Developers
Classifier: License :: OSI Approved :: Apache Software License
Classifier: Natural Language :: English
Classifier: Operating System :: MacOS :: MacOS X
Classifier: Operating System :: POSIX
Classifier: Programming Language :: Python :: 3
Classifier: Programming Language :: Python :: 3.7
Classifier: Programming Language :: Python :: 3.8
Classifier: Programming Language :: Python :: 3.9
Classifier: Topic :: Communications
Classifier: Topic :: System :: Networking
Requires-Dist: aioredis (>=1.2.0)
Requires-Dist: jsonschema (>=3.2)
Requires-Dist: pyyaml (>=3.12)
Project-URL: Documentation, https://lightbus.org
Project-URL: Repository, https://github.com/adamcharnock/lightbus/
